forecast_sdk/__init__.py
forecast_sdk/forecast_pipeline.py
forecast_sdk-0.1.0.dist-info/METADATA
forecast_sdk-0.1.0.dist-info/WHEEL
forecast_sdk-0.1.0.dist-info/top_level.txt
forecast_sdk-0.1.0.dist-info/RECORD
