Metadata-Version: 2.1
Name: forecast-sdk
Version: 0.1.0
Summary: A time series forecasting SDK using XGBoost and ARIMA
Home-page: UNKNOWN
Author: Your Name
Author-email: your.email@example.com
License: UNKNOWN
Platform: UNKNOWN
Classifier: Programming Language :: Python :: 3
Classifier: Operating System :: OS Independent
Requires-Dist: numpy
Requires-Dist: pandas
Requires-Dist: python-dateutil
Requires-Dist: scikit-learn
Requires-Dist: statsmodels
Requires-Dist: streamlit
Requires-Dist: xgboost
